MANIFEST.in
README
README.txt
setup.py
src/nous/__init__.py
src/nous.pylons.testing.egg-info/PKG-INFO
src/nous.pylons.testing.egg-info/SOURCES.txt
src/nous.pylons.testing.egg-info/dependency_links.txt
src/nous.pylons.testing.egg-info/namespace_packages.txt
src/nous.pylons.testing.egg-info/not-zip-safe
src/nous.pylons.testing.egg-info/requires.txt
src/nous.pylons.testing.egg-info/top_level.txt
src/nous/pylons/__init__.py
src/nous/pylons/testing/__init__.py
src/nous/pylons/testing/browser.py