Metadata-Version: 1.0
Name: nous.pylons.testing
Version: 0.4.7
Summary: Nous testing utils.
Home-page: http://github.com/Ignas/nous.pylons.testing/
Author: Ignas Mikalajunas
Author-email: ignas@nous.lt
License: GPL
Platform: UNKNOWN
Classifier: Development Status :: 3 - Alpha
Classifier: Environment :: Web Environment
Classifier: Topic :: Communications :: Email
Classifier: Intended Audience :: Developers
Classifier: License :: OSI Approved :: GNU General Public License (GPL)
Classifier: Programming Language :: Python
